bootstrap/__init__.py
bootstrap/app.py
bootstrap/routes.yml
bootstrap/runner.py
bootstrap/wsgi.py
bootstrap/config/__init__.py
bootstrap/config/base.py
bootstrap/config/config_yaml.py
routing/__init__.py
routing/controllers/__init__.py
routing/controllers/health.py
routing/controllers/router.py
routing/controllers/response/__init__.py
routing/controllers/response/custom_response.py
routing/infrastructure/__init__.py
routing/infrastructure/proxy/__init__.py
routing/infrastructure/proxy/openrouteservice/__init__.py
routing/infrastructure/proxy/openrouteservice/distancematrix_adapter.py
routing/infrastructure/proxy/openrouteservice/distancematrix_client.py
routing/optimization/__init__.py
routing/optimization/vrp_solver.py
routing/services/__init__.py
routing/services/router_service.py
tests/__init__.py
tests/routing/__init__.py
tests/routing/controllers/__init__.py
tests/routing/controllers/test_router.py
tests/routing/controllers/response/__init__.py
tests/routing/controllers/response/test_custom_response.py
tests/routing/infrastructure/__init__.py
tests/routing/infrastructure/proxy/__init__.py
tests/routing/infrastructure/proxy/openrouteservice/__init__.py
tests/routing/infrastructure/proxy/openrouteservice/test_distancematrix_adapter.py
tests/routing/infrastructure/proxy/openrouteservice/test_distancematrix_client.py
tests/routing/optimization/__init__.py
tests/routing/optimization/test_vrp_solver.py
tests/routing/services/__init__.py
tests/routing/services/test_router_service.py
utils/__init__.py
utils/fillable_entity.py
und_route_optimization-0.0.7.dist-info/METADATA
und_route_optimization-0.0.7.dist-info/WHEEL
und_route_optimization-0.0.7.dist-info/entry_points.txt
und_route_optimization-0.0.7.dist-info/top_level.txt
und_route_optimization-0.0.7.dist-info/RECORD
