Metadata-Version: 2.1
Name: und-route-optimization
Version: 0.0.7
Summary: servidor para optimizacion de rutas
Home-page: https://github.com/und-tech/und-python-microservice
Author: UND
Author-email: development@orbis.com.pe
License: UNKNOWN
Platform: UNKNOWN
Classifier: Programming Language :: Python :: 3
Classifier: License :: OSI Approved :: MIT License
Classifier: Operating System :: OS Independent
Requires-Dist: PyYAML (==3.12)
Requires-Dist: coverage (==4.5.1)
Requires-Dist: dataclasses
Requires-Dist: falcon (==2.0.0)
Requires-Dist: gunicorn (==20.0.4)
Requires-Dist: injector (==0.18.3)
Requires-Dist: nose (==1.3.7)
Requires-Dist: ortools
Requires-Dist: pylint (==1.8.4)
Requires-Dist: requests (==2.23.0)
